LICENSE
MANIFEST.in
requirements.txt
setup.cfg
setup.py
test_requirements.txt
eth_owned/__init__.py
eth_owned/owned.py
eth_owned/void.py
eth_owned.egg-info/PKG-INFO
eth_owned.egg-info/SOURCES.txt
eth_owned.egg-info/dependency_links.txt
eth_owned.egg-info/entry_points.txt
eth_owned.egg-info/requires.txt
eth_owned.egg-info/top_level.txt
eth_owned/data/Owned.bin
eth_owned/data/Owned.json
eth_owned/data/OwnedSimple.bin
eth_owned/data/OwnedSimple.json
eth_owned/data/VoidOwner.bin
eth_owned/data/VoidOwner.json
eth_owned/data/__init__.py
eth_owned/runnable/owner.py
eth_owned/runnable/void.py
eth_owned/runnable/void_deploy.py
eth_owned/unittest/__init__.py
eth_owned/unittest/base.py
eth_owned/unittest/interface.py
tests/test_owned.py